{
  "alstertal:450aaa838696": {
    "first_seen": "2026-07-07T18:53:14.019631+00:00",
    "id": "alstertal:450aaa838696",
    "last_seen": "2026-07-07T18:53:14.019631+00:00",
    "living_area": 175.0,
    "objektart": null,
    "ort": "22397 Hamburg-Duvenstedt",
    "plot_area": null,
    "price": null,
    "price_per_sqm": null,
    "source": "alstertal",
    "status": "pending",
    "title": "Toskana-Stadtvilla in idyllischer Feldrandlage",
    "url": "https://www.alstertal-immo.de/immobilienangebote/"
  },
  "alstertal:9f402183494c": {
    "first_seen": "2026-07-07T18:53:14.019631+00:00",
    "id": "alstertal:9f402183494c",
    "last_seen": "2026-07-07T18:53:14.019631+00:00",
    "living_area": 130.0,
    "objektart": null,
    "ort": "22397 Hamburg-Duvenstedt",
    "plot_area": null,
    "price": null,
    "price_per_sqm": null,
    "source": "alstertal",
    "status": "sold",
    "title": "Am Feldrand. Am Leben. Am richtigen Ort.",
    "url": "https://www.alstertal-immo.de/immobilienangebote/"
  },
  "alstertal:b0d4fe2928e0": {
    "first_seen": "2026-07-07T18:53:14.019631+00:00",
    "id": "alstertal:b0d4fe2928e0",
    "last_seen": "2026-07-07T18:53:14.019631+00:00",
    "living_area": 81.9,
    "objektart": null,
    "ort": "22393 Hamburg-Sasel",
    "plot_area": null,
    "price": null,
    "price_per_sqm": null,
    "source": "alstertal",
    "status": "pending",
    "title": "Penthouse mit Potenzial",
    "url": "https://www.alstertal-immo.de/immobilienangebote/"
  },
  "alstertal:bf07923164e8": {
    "first_seen": "2026-07-07T18:53:14.019631+00:00",
    "id": "alstertal:bf07923164e8",
    "last_seen": "2026-07-07T18:53:14.019631+00:00",
    "living_area": null,
    "objektart": null,
    "ort": "22393 Hamburg-Sasel",
    "plot_area": 731.0,
    "price": null,
    "price_per_sqm": null,
    "source": "alstertal",
    "status": "pending",
    "title": "Sonniges Baugrundstück in Südwestlage",
    "url": "https://www.alstertal-immo.de/immobilienangebote/"
  },
  "alstertal:cc2300240032": {
    "first_seen": "2026-07-07T18:53:14.019631+00:00",
    "id": "alstertal:cc2300240032",
    "last_seen": "2026-07-07T18:53:14.019631+00:00",
    "living_area": null,
    "objektart": null,
    "ort": "22393 Hamburg-Sasel",
    "plot_area": 440.0,
    "price": null,
    "price_per_sqm": null,
    "source": "alstertal",
    "status": "pending",
    "title": "Baugrundstück in ruhiger Lage",
    "url": "https://www.alstertal-immo.de/immobilienangebote/"
  },
  "alstertal:f3500966838e": {
    "first_seen": "2026-07-07T18:53:14.019631+00:00",
    "id": "alstertal:f3500966838e",
    "last_seen": "2026-07-07T18:53:14.019631+00:00",
    "living_area": null,
    "objektart": null,
    "ort": "22393 Hamburg - Sasel",
    "plot_area": null,
    "price": null,
    "price_per_sqm": null,
    "source": "alstertal",
    "status": "pending",
    "title": "Frahmredder 49",
    "url": "https://www.alstertal-immo.de/immobilienangebote/"
  },
  "bayer:6203": {
    "first_seen": "2026-07-07T18:53:14.019631+00:00",
    "id": "bayer:6203",
    "last_seen": "2026-07-07T18:53:14.019631+00:00",
    "living_area": null,
    "objektart": null,
    "ort": "Schönes Baugrundstück mit Altbestand in Poppenbüttel",
    "plot_area": 907.0,
    "price": 560000.0,
    "price_per_sqm": null,
    "source": "bayer",
    "status": "Kauf",
    "title": "Schönes Baugrundstück mit Altbestand in Poppenbüttel",
    "url": "https://bayer-hamburg.de/angebot/schoenes-baugrundstueck-mit-altbestand-in-poppenbuettel"
  },
  "bayer:6285": {
    "first_seen": "2026-07-07T18:53:14.019631+00:00",
    "id": "bayer:6285",
    "last_seen": "2026-07-07T18:53:14.019631+00:00",
    "living_area": 162.0,
    "objektart": null,
    "ort": "Großzügiges Grundstück - Einfamilienhaus mit Sanierungsbedarf in Duvenstedt",
    "plot_area": 1997.0,
    "price": 755000.0,
    "price_per_sqm": 4660.49,
    "source": "bayer",
    "status": "Kauf",
    "title": "Großzügiges Grundstück - Einfamilienhaus mit Sanierungsbedarf in Duvenstedt",
    "url": "https://bayer-hamburg.de/angebot/grosszuegiges-grundstueck-einfamilienhaus-mit-sanierungsbedarf-in-duvenstedt"
  },
  "hintzhintz:1006": {
    "first_seen": "2026-07-07T18:53:14.019631+00:00",
    "id": "hintzhintz:1006",
    "last_seen": "2026-07-07T18:53:14.019631+00:00",
    "living_area": null,
    "objektart": "Einfamilienhaus",
    "ort": "22395 Hamburg Wohldorf-Ohlstedt",
    "plot_area": null,
    "price": null,
    "price_per_sqm": null,
    "source": "hintzhintz",
    "status": "Kauf",
    "title": "",
    "url": "https://hintzundhintz.de/immobilien/gut-verkauft-alles-bequem-auf-einer-ebene-ruhig-und-doch-nah-bei"
  },
  "hintzhintz:1012": {
    "first_seen": "2026-07-07T18:53:14.019631+00:00",
    "id": "hintzhintz:1012",
    "last_seen": "2026-07-07T18:53:14.019631+00:00",
    "living_area": null,
    "objektart": "Einfamilienhaus",
    "ort": "22397 Hamburg Duvenstedt",
    "plot_area": null,
    "price": 1265.0,
    "price_per_sqm": null,
    "source": "hintzhintz",
    "status": "Miete",
    "title": "",
    "url": "https://hintzundhintz.de/immobilien/gut-vermietet-idyllisches-wohnen-im-denkmalgeschuetztem-reetdachhaus"
  },
  "hintzhintz:1013": {
    "first_seen": "2026-07-07T18:53:14.019631+00:00",
    "id": "hintzhintz:1013",
    "last_seen": "2026-07-07T18:53:14.019631+00:00",
    "living_area": null,
    "objektart": "Einfamilienhaus",
    "ort": "22393 Hamburg Sasel",
    "plot_area": null,
    "price": null,
    "price_per_sqm": null,
    "source": "hintzhintz",
    "status": "Kauf",
    "title": "",
    "url": "https://hintzundhintz.de/immobilien/gut-verkauft-hamburger-kaffeemuehle-grossartiges-familiendomizil"
  },
  "hintzhintz:1015": {
    "first_seen": "2026-07-07T18:53:14.019631+00:00",
    "id": "hintzhintz:1015",
    "last_seen": "2026-07-07T18:53:14.019631+00:00",
    "living_area": null,
    "objektart": "Grundstück",
    "ort": "22147 Hamburg Rahlstedt",
    "plot_area": null,
    "price": null,
    "price_per_sqm": null,
    "source": "hintzhintz",
    "status": "Kauf",
    "title": "",
    "url": "https://hintzundhintz.de/immobilien/gut-verkauft-grosses-einfamilienhaus-baugrundstueck-mit-idealen-moeglichkeiten-fuer-projektierer"
  }
}